LICENSE.rst
MANIFEST.in
README.rst
TODO.rst
setup.py
PyMail.egg-info/PKG-INFO
PyMail.egg-info/SOURCES.txt
PyMail.egg-info/dependency_links.txt
PyMail.egg-info/entry_points.txt
PyMail.egg-info/requires.txt
PyMail.egg-info/top_level.txt
pymail/__init__.py
pymail/authenticator.py
pymail/authorisation.py
pymail/client.py
pymail/configuration.py
pymail/debug.py
pymail/error.py
pymail/greenfile.py
pymail/main.py
pymail/server.py
pymail/sink.py
pymail/smtp.py
pymail/spooler.py
pymail/etc/pymail
pymail/etc/pymail/cert.pem
pymail/etc/pymail/config
pymail/etc/pymail/key.pem
test/test10.py
test/test20.py
test/test40.py